[
	{
		"id": "typescript-compiler",
		"title": "Unleashing the TypeScript Compiler",
		"date": "June 2024",
		"url": "/talks/unleashing-the-typescript-compiler",
		"location": "THAT Conference 2024",
		"promote": true,
		"source": "youtube",
		"type": "talk",
		"remote": false,
		"multiple": true,
		"img": "typescript-compiler.jpg"
	},
	{
		"id": "state-talk",
		"title": "Componentizing Application State",
		"location": "THAT Conference 2024",
		"date": "January 2024",
		"url": "/talks/componentizing-application-state",
		"videoId": "4-msZqqrN1A",
		"promote": true,
		"source": "page",
		"type": "talk",
		"remote": false,
		"multiple": true
	},
	{
		"id": "tsconf-ts-team-2021",
		"title": "TalkScript with the TypeScript Team",
		"date": "October 2021",
		"location": "TSConf 2021",
		"url": "https://www.youtube.com/watch?v=gfn-aKykyAM",
		"videoId": "gfn-aKykyAM",
		"source": "youtube",
		"type": "panel",
		"remote": true
	},
	{
		"id": "js-trends-2021",
		"title": "JavaScript Trends Revisited",
		"date": "March 2021",
		"location": "OpenJS Foundation",
		"url": "https://www.youtube.com/watch?v=mYIydmcdRDA",
		"videoId": "mYIydmcdRDA",
		"source": "youtube",
		"type": "panel",
		"remote": true
	},
	{
		"id": "js-trends-2020",
		"title": "2020 Tech Trends Predictions",
		"date": "December 2019",
		"location": "Node+JS Interactive 2019",
		"url": "https://www.youtube.com/watch?v=By1-aNeGQ9U&list",
		"videoId": "By1-aNeGQ9U",
		"source": "youtube",
		"type": "panel",
		"remote": false
	},
	{
		"id": "tsconf-ts-team-2019",
		"title": "TalkScript with the TypeScript Team",
		"date": "October 2019",
		"location": "TSConf 2019",
		"url": "https://www.youtube.com/watch?v=obvOZn639ms",
		"videoId": "obvOZn639ms",
		"source": "youtube",
		"type": "panel",
		"remote": false
	},
	{
		"id": "rules-to-git-by",
		"title": "Rules to Git By",
		"date": "October 2019",
		"location": "NebraskaJS",
		"url": "https://www.youtube.com/watch?v=aHKn59spc6M",
		"videoId": "aHKn59spc6M",
		"source": "youtube",
		"promote": true,
		"type": "talk",
		"remote": false
	},
	{
		"id": "no-time-for-types",
		"title": "No Time for Types",
		"date": "August 2018",
		"location": "JSConf US 2018",
		"url": "https://www.youtube.com/watch?v=qGK541P2xII",
		"videoId": "qGK541P2xII",
		"source": "youtube",
		"type": "talk",
		"remote": false
	},
	{
		"id": "tsconf-ts-team-2018",
		"title": "TalkScript with the TypeScript Team",
		"date": "March 2018",
		"location": "TSConf 2018",
		"url": "https://www.youtube.com/watch?v=MxB0ldQfvT4",
		"videoId": "MxB0ldQfvT4",
		"source": "youtube",
		"type": "panel",
		"remote": false
	},
	{
		"id": "js-metaprogramming",
		"title": "JavaScript Metaprogramming",
		"date": "March 2016",
		"location": "NebraskaJS",
		"url": "https://www.youtube.com/watch?v=nsG_izwv_0U",
		"videoId": "nsG_izwv_0U",
		"source": "youtube",
		"type": "talk",
		"remote": false
	},
	{
		"id": "neovim-intro-2015",
		"title": "Neovim",
		"date": "October 2015",
		"location": "Omaha Ruby and Open Source Meetup",
		"url": "https://www.youtube.com/watch?v=LRQGAnPtNdM",
		"videoId": "LRQGAnPtNdM",
		"source": "youtube",
		"type": "talk",
		"remote": false
	},
	{
		"id": "js-fundamentals-2015",
		"title": "JavaScript Fundamentals",
		"date": "May 2015",
		"location": "JSConf 2015",
		"url": "http://2015.jsconf.us/speakers.html#nisi",
		"source": "website",
		"type": "workshop",
		"remote": false
	},
	{
		"id": "vim-tmux",
		"title": "vim  + tmux",
		"date": "February 2015",
		"location": "OMG!Code",
		"url": "https://www.youtube.com/watch?v=5r6yzFEXajQ",
		"videoId": "5r6yzFEXajQ",
		"source": "youtube",
		"remote": false,
		"type": "talk",
		"promote": false
	},
	{
		"id": "modern-dojo-2015",
		"title": "Modern Dojo",
		"date": "January 2015",
		"location": "NebraskaJS Lincoln",
		"url": "https://www.youtube.com/watch?v=__7Fg1h_N6w",
		"videoId": "__7Fg1h_N6w",
		"source": "youtube",
		"type": "talk",
		"remote": false
	},
	{
		"id": "intern-in-action",
		"title": "Intern in Action",
		"date": "January 2015",
		"location": "Omaha Ruby and Open Source Meetup",
		"url": "https://www.youtube.com/watch?v=oOssM0DusYc",
		"videoId": "oOssM0DusYc",
		"source": "youtube",
		"type": "talk",
		"remote": false
	},
	{
		"id": "intern-intro",
		"title": "Intro to Intern",
		"date": "January 2015",
		"location": "Omaha Coffee and Code",
		"url": "https://www.youtube.com/watch?v=Fgt_frjlAaQ",
		"videoId": "Fgt_frjlAaQ",
		"source": "youtube",
		"type": "talk",
		"remote": false
	},
	{
		"id": "typscript-intro-2014",
		"title": "TypeScript",
		"date": "November 2014",
		"location": "NebraskaJS",
		"url": "https://www.youtube.com/watch?v=nLCedy68Qf4",
		"videoId": "nLCedy68Qf4",
		"source": "youtube",
		"type": "talk",
		"remote": false
	},
	{
		"id": "chrome-extensions-2014",
		"title": "Building Chrome Extensions",
		"date": "July 2014",
		"location": "NebraskaJS",
		"url": "https://www.youtube.com/watch?v=HzJ9pUWb2rA",
		"videoId": "HzJ9pUWb2rA",
		"source": "youtube",
		"type": "talk",
		"remote": false
	},
	{
		"id": "open-source-2014",
		"title": "Contributing to Open Source",
		"date": "May 2014",
		"location": "NebraskaJS",
		"url": "https://vimeo.com/99035913",
		"videoId": "99035913",
		"source": "vimeo",
		"type": "talk",
		"remote": false
	},
	{
		"id": "leapcopter",
		"title": "Leapcopter",
		"date": "January 2014",
		"location": "NebraskaJS",
		"url": "https://vimeo.com/83939999",
		"videoId": "83939999",
		"source": "vimeo",
		"type": "talk",
		"remote": false
	},
	{
		"id": "node-2013",
		"title": "Building RESTful Services with Node.js",
		"date": "January 2013",
		"location": "NebraskaJS",
		"url": "https://www.youtube.com/watch?v=APO3fFH7osw",
		"source": "youtube",
		"videoId": "APO3fFH7osw",
		"type": "talk",
		"remote": false
	},
	{
		"id": "node-2012",
		"title": "Node.js and Express",
		"date": "November 2012",
		"location": "Omaha Dynamic Language Users Group",
		"url": "https://www.youtube.com/watch?v=h38DDvmVag0",
		"source": "youtube",
		"videoId": "h38DDvmVag0",
		"type": "talk",
		"remote": false
	},
	{
		"id": "vim-2012",
		"title": "I <3 vim",
		"date": "September 2012",
		"location": "Barcamp Omaha",
		"url": "https://www.youtube.com/watch?v=oHoei-MXYiw",
		"source": "youtube",
		"videoId": "oHoei-MXYiw",
		"type": "talk",
		"remote": false
	},
	{
		"id": "amd-require",
		"title": "AMD and RequireJS",
		"date": "August 2012",
		"location": "Omaha Dynamic Language Users Group",
		"url": "https://www.youtube.com/watch?v=PhHHlY_gIXE",
		"source": "youtube",
		"videoId": "PhHHlY_gIXE",
		"type": "talk",
		"remote": false
	}
]
